cdk_daily_spend_to_slack/__init__.py
cdk_daily_spend_to_slack/py.typed
cdk_daily_spend_to_slack/_jsii/__init__.py
cdk_daily_spend_to_slack/_jsii/daily-spend-to-slack@0.0.3.jsii.tgz
cdk_daily_spend_to_slack-0.0.3.dist-info/LICENSE
cdk_daily_spend_to_slack-0.0.3.dist-info/METADATA
cdk_daily_spend_to_slack-0.0.3.dist-info/WHEEL
cdk_daily_spend_to_slack-0.0.3.dist-info/top_level.txt
cdk_daily_spend_to_slack-0.0.3.dist-info/RECORD
