Metadata-Version: 2.1
Name: cdk-daily-spend-to-slack
Version: 0.0.3
Summary: daily-spend-to-slack
Home-page: https://github.com/stroobants-dev/daily-spend-to-slack.git
Author: Tom Stroobants<tom@stroobants.dev>
License: MPL-2.0
Project-URL: Source, https://github.com/stroobants-dev/daily-spend-to-slack.git
Platform: UNKNOWN
Classifier: Intended Audience :: Developers
Classifier: Operating System :: OS Independent
Classifier: Programming Language :: JavaScript
Classifier: Programming Language :: Python :: 3 :: Only
Classifier: Programming Language :: Python :: 3.6
Classifier: Programming Language :: Python :: 3.7
Classifier: Programming Language :: Python :: 3.8
Classifier: Programming Language :: Python :: 3.9
Classifier: Typing :: Typed
Classifier: Development Status :: 5 - Production/Stable
Classifier: License :: OSI Approved
Requires-Python: >=3.6
License-File: LICENSE
Requires-Dist: aws-cdk-lib (<3.0.0,>=2.0.0)
Requires-Dist: constructs (<11.0.0,>=10.0.5)
Requires-Dist: jsii (<2.0.0,>=1.49.0)
Requires-Dist: publication (>=0.0.3)
